bd09convertor/__init__.py
bd09convertor-0.0.2.dist-info/LICENSE
bd09convertor-0.0.2.dist-info/METADATA
bd09convertor-0.0.2.dist-info/WHEEL
bd09convertor-0.0.2.dist-info/top_level.txt
bd09convertor-0.0.2.dist-info/RECORD
