Metadata-Version: 2.1
Name: bd09convertor
Version: 0.0.2
Summary: BD09 coordinates conversion tool for Python.
Home-page: https://github.com/46319943/BD09Convertor
Author: Piao Yang
Author-email: 495384481@qq.com
Classifier: Programming Language :: Python :: 3
Classifier: License :: OSI Approved :: MIT License
Classifier: Operating System :: OS Independent
Requires-Python: >=3.5
License-File: LICENSE
